LICENSE.txt
MANIFEST.in
README.md
README.rst
setup.py
nttpipeline/__init__.py
nttpipeline/__version__.py
nttpipeline/cl_utils.py
nttpipeline/default_settings.yaml
nttpipeline/setup.cfg
nttpipeline/utKit.py
nttpipeline.egg-info/PKG-INFO
nttpipeline.egg-info/SOURCES.txt
nttpipeline.egg-info/dependency_links.txt
nttpipeline.egg-info/not-zip-safe
nttpipeline.egg-info/requires.txt
nttpipeline.egg-info/top_level.txt
nttpipeline/commonutils/__init__.py
nttpipeline/commonutils/getpackagepath.py
nttpipeline/tests/__init__.py