Metadata-Version: 1.1
Name: nttpipeline
Version: 0.1
Summary: A python package and command-line tools to A command-line data-reduction pipeline for the NTT EFOSC and SOFI instruments
Home-page: https://github.com/thespacedoctor/nttpipeline
Author: David Young
Author-email: davidrobertyoung@gmail.com
License: MIT
Download-URL: https://github.com/thespacedoctor/nttpipeline/archive/v0.1.zip
Keywords: ntt, astronomy, efosc, sofi, pessto, pipeline
Platform: UNKNOWN
Classifier: Development Status :: 4 - Beta
Classifier: License :: OSI Approved :: MIT License
Classifier: Programming Language :: Python :: 2.7
Classifier: Topic :: Utilities
